wazy/__init__.py
wazy/asktell.py
wazy/e2e.py
wazy/mlp.py
wazy/seq.py
wazy/utils.py
wazy/version.py
wazy-0.12.1.dist-info/LICENSE
wazy-0.12.1.dist-info/METADATA
wazy-0.12.1.dist-info/WHEEL
wazy-0.12.1.dist-info/top_level.txt
wazy-0.12.1.dist-info/zip-safe
wazy-0.12.1.dist-info/RECORD
