Metadata-Version: 2.1
Name: wazy
Version: 0.12.1
Summary: Pretrained Bayesian Optimization of Sequences
Home-page: http://thewhitelab.org/Software
Author: Ziyue Yang, Andrew White
Author-email: andrew.white@rochester.edu
License: MIT
Classifier: Programming Language :: Python :: 3
Classifier: License :: OSI Approved :: MIT License
Classifier: Operating System :: OS Independent
Classifier: Topic :: Scientific/Engineering :: Bio-Informatics
Classifier: Topic :: Scientific/Engineering :: Artificial Intelligence
License-File: LICENSE
Requires-Dist: jax
Requires-Dist: dm-haiku
Requires-Dist: optax
Requires-Dist: numpy
Requires-Dist: jax-unirep
